{"-3": {"у + GEN": ["Следующим по списку У ТОВАРИЩА Парфенова ЗНАЧИТСЯ пароход\" Бургас\"."]}, "-2": {}, "-1": {"NOM": ["А почему ОНО ЗНАЧИТСЯ как\" первое\"?", "Где же тут НОМЕРА ЗНАЧАТСЯ?"], "GEN": ["Следующим по списку у товарища ПАРФЕНОВА ЗНАЧИТСЯ пароход\" Бургас\"."]}, "0": {}, "1": {"NOM": ["Через несколько дней она прислала за вещами первой необходимости, среди которых не ЗНАЧИЛАСЬ ПОЛУТОРАГОДОВАЛАЯ дочка.", "Следующим по списку у товарища Парфенова ЗНАЧИТСЯ ПАРОХОД\" Бургас\"."], "под + INST": ["Я решила принять участие в конкурсе на должность главного бухгалтера-- в списке соискателей, кстати, я ЗНАЧИЛАСЬ ПОД НОМЕРОМ 13."]}, "2": {}, "3": {}}