{"-3": {}, "-2": {}, "-1": {"DAT": ["А вам ЗАХОТЕЛОСЬ ПЕРЕЧИТАТЬ\" Идиота\"?", "Сейчас вот мне ЗАХОТЕЛОСЬ ПЕРЕЧИТАТЬ Булгакова/ начала\" Мастер и Маргарита\" читать.", "Да/ вот мне ЗАХОТЕЛОСЬ ПЕРЕЧИТАТЬ."]}, "0": {}, "1": {"ACC": ["Андрей ПЕРЕЧИТАЛ ПИСЬМО, повертел его в пальцах, сложил и сунул назад в конверт.", "Ему захотелось ПЕРЕЧИТАТЬ ПИСЬМО, и он вытащил сложённый вдвое конверт из кармана.", "Андрей включил лампочку над подушкой, достал письмо и ПЕРЕЧИТАЛ ЕГО-- никакого постскриптума там не было.", "Сейчас вот мне захотелось ПЕРЕЧИТАТЬ БУЛГАКОВА/ начала\" Мастер и Маргарита\" читать."]}, "2": {}, "3": {}}