{"-3": {}, "-2": {}, "-1": {"ACC": ["Но головка, всякий РАЗ ПРИДАВИВ обшарпанную пластинку( которая волнообразно покачивалась, а на ней, в центре, на круглом красном ярлыке, сливались в нерасторжимом союзе рабочий и колхозница, а также их орудия труда),-- головка с иглой, пощелкав по самому сердцу, извлекала неизвестно откуда голос Раджа Капура:"]}, "0": {}, "1": {"ACC": ["Но головка, всякий раз ПРИДАВИВ ОБШАРПАННУЮ пластинку( которая волнообразно покачивалась, а на ней, в центре, на круглом красном ярлыке, сливались в нерасторжимом союзе рабочий и колхозница, а также их орудия труда),-- головка с иглой, пощелкав по самому сердцу, извлекала неизвестно откуда голос Раджа Капура:"]}, "2": {}, "3": {}}