{"-3": {"в/во + ACC": ["Было половина первого, а В ТРИ меня РАЗБУДИЛИ."]}, "-2": {}, "-1": {"ACC": ["Утром НАС РАЗБУДИЛИ брезгливые голоса.", "Было половина первого, а в три МЕНЯ РАЗБУДИЛИ.", "Как всегда, АНДРЕЯ РАЗБУДИЛО радио-- бескрайний баритон читал стихи:", "Я это оцениваю узко практически-- надо КОГО-ТО РАЗБУДИТЬ, заставить взглянуть на Достоевского более внимательно."]}, "0": {}, "1": {"NOM": ["Его РАЗБУДИЛ ВЗРЫВ, он выскочил и увидел, что угол основательно разворочен-- кто-то использовал неведомое взрывное устройство.", "Утром нас РАЗБУДИЛИ БРЕЗГЛИВЫЕ голоса.", "Андрея РАЗБУДИЛ ОБЫЧНЫЙ утренний шум-- бодрые разговоры в туалетной очереди, уже заполнившей коридор, отчаянный детский плач за тонкой стенкой и близкий храп.", "Как всегда, Андрея РАЗБУДИЛО РАДИО-- бескрайний баритон читал стихи:", "РАЗБУДИЛИ МЫ тебя всё-таки/ да?"], "ACC": ["Варя РАЗБУДИЛА ШОФЁРА."]}, "2": {}, "3": {}}