{"-3": {}, "-1": {"NOM": ["Характерно то, что избыточность физической тяжести придаёт движению его руки такую весомость, что ОН УСАЖИВАЕТ вашу компанию, почти не глядя или даже не глядя на неё, из чего следует, что компания, всполошившись, правильно сделала."]}, "1": {"ACC": ["Характерно то, что избыточность физической тяжести придаёт движению его руки такую весомость, что он УСАЖИВАЕТ ВАШУ компанию, почти не глядя или даже не глядя на неё, из чего следует, что компания, всполошившись, правильно сделала."]}}