{"-3": {}, "-2": {}, "-1": {"INST": ["Пушкин этим ОПРЕДЕЛЕНИЕМ ВОЗВОДИТСЯ также в ранг поэта абсолютного( ранг, которого вознамерилось в 1925 г. лишить его историко-литературное изучение, объявившее демифологизацию Пушкина: см. цитату из книги Б. В. Томашевского на первой странице настоящей статьи)."]}, "0": {}, "1": {}, "2": {"в/во + ACC": ["Пушкин этим определением ВОЗВОДИТСЯ также В РАНГ поэта абсолютного( ранг, которого вознамерилось в 1925 г. лишить его историко-литературное изучение, объявившее демифологизацию Пушкина: см. цитату из книги Б. В. Томашевского на первой странице настоящей статьи)."]}, "3": {}}