{"-3": {}, "-2": {}, "-1": {"INST": ["Не исключено, что ВТОРЫМИ ДОБЫВАТЬ деньги из мусора станет Сочи.", "Жители местной деревеньки Хандумон ВЕКАМИ ДОБЫВАЛИ морских коньков."], "NOM": ["\" Он ПОШЁЛ ДОБЫВАТЬ себе лавры в\" Единстве\", но его туда не взяли, и теперь он находится в интересном положении,-- ехидничал Геннадий Райков, говоря о\" ренегате\" Рогозине."], "ACC": ["По словам Аманды Винсент, каждый ГОД ДОБЫВАЮТ не менее 26 миллионов этих рыб."]}, "0": {}, "1": {"ACC": ["Моя целевая аудитория-- город, где работает компания, там, где мы ДОБЫВАЕМ НЕФТЬ.", "Быстро развели огонь, и я принялся ДОБЫВАТЬ РЫБУ на уху, дочь и Коля таскали хворост и коряжины на ночной костёр.", "Не исключено, что вторыми ДОБЫВАТЬ ДЕНЬГИ из мусора станет Сочи.", "Но тогда его просто придушат в переходах теремного дворца или запытают в подземелье, ДОБЫВАЯ КЛЮЧИ от клада.", "Жители местной деревеньки Хандумон веками ДОБЫВАЛИ МОРСКИХ коньков."], "DAT": ["\" Он пошёл ДОБЫВАТЬ СЕБЕ лавры в\" Единстве\", но его туда не взяли, и теперь он находится в интересном положении,-- ехидничал Геннадий Райков, говоря о\" ренегате\" Рогозине.", "Российские спецслужбы\" отвязаны\", находятся на беспривязном содержании, ДОБЫВАЮТ СЕБЕ корм, где хотят."]}, "2": {"из + GEN": ["Не исключено, что вторыми ДОБЫВАТЬ деньги ИЗ МУСОРА станет Сочи."]}, "3": {}}