{"-3": {}, "-2": {}, "-1": {"ACC": ["Хотя что может теперь МЕНЯ НАПУГАТЬ?"], "GEN": ["Лично меня и мою семью 11 СЕНТЯБРЯ НАПУГАЛО очень здорово."], "NOM": ["Что ОНИ НАПУГАЛИ мир/ что они вcё-таки сила."]}, "0": {}, "1": {"NOM": ["Уверен— НАПУГАЮТ РВАНЫЕ жестяные лабиринты гаражей в районе Комсомолки, с вечной жирной грязью на дороге, пропитанной венозной кровью трех поколений тушинских хулиганов."], "ACC": ["Чего там, НАПУГАТЬ ЛЮДЕЙ просто, а вот...", "НАПУГАТЬ ЖЕГЛОВА.", "Но НАПУГАТЬ ЖЕГЛОВА-- кишка тонка\".", "Что они НАПУГАЛИ МИР/ что они вcё-таки сила."]}, "2": {}, "3": {}}