{"-3": {}, "-2": {}, "-1": {"NOM": ["Так и теперь, каждый раз, когда МЫСЛЬ ПОДБИРАЛАСЬ к определённому пласту, голос приговаривал:\" Теплее, ищи здесь\".", "Вот/ ну/ это на целых две программы/ пока они есть не полностью- но вcё-таки уже так Я ПОДБИРАЮСЬ потихонечку.\""], "GEN": ["Параметры нормальных РАСПРЕДЕЛЕНИЙ ПОДБИРАЮТСЯ так, чтобы обеспечить наилучшее согласование с наблюдениями."], "INST": ["Они к нам таким ОБРАЗОМ ПОДБИРАЮТСЯ."]}, "0": {}, "1": {"к + DAT": ["Так и теперь, каждый раз, когда мысль ПОДБИРАЛАСЬ К ОПРЕДЕЛЁННОМУ пласту, голос приговаривал:\" Теплее, ищи здесь\"."], "NOM": ["А ПОДБИРАТЬСЯ ЭТА линия должна исключительно экспериментальным путём."], "из + GEN": ["Правило построения структурного конструкторского решения следующее: выбирается узел, помеченный парой n: t, затем к выбранному узлу добавляются подчинённые узлы, которые ПОДБИРАЮТСЯ ИЗ РАЗДЕЛОВ\" Состав\" и\" Параметры\" описания конструкторского понятия t."]}, "2": {}, "3": {}}