{"-3": {}, "-2": {}, "-1": {"NOM": ["Срочно, потому что судорожные СОСТОЯНИЯ РАЗРУШАЮТ нервную систему.", "Ибо ОН РАЗРУШАЕТ основания не только всех известных астрономических систем, но и всей предшествующей космологии."], "GEN": ["Десять ЛЕТ РАЗРУШАЛИ."]}, "0": {}, "1": {"ACC": ["Срочно, потому что судорожные состояния РАЗРУШАЮТ НЕРВНУЮ систему.", "А ответный гол Холуба в том, что даже вальяжная и разрозненная атака\" Спарты\" способна легко РАЗРУШАТЬ ЗАЩИТУ Романцева.", "Ибо он РАЗРУШАЕТ ОСНОВАНИЯ не только всех известных астрономических систем, но и всей предшествующей космологии.", "Витгенштейн убедительно РАЗРУШАЕТ ИЛЛЮЗИЮ, что математику якобы можно отделить от физической реальности."], "GEN": ["Он соизмерял сегодняшние события с историческими фактами, цитируя Павла Рябушинского:\" Господа социал-демократы, не РАЗРУШАЙТЕ ЗДАНИЯ, в котором мы живём\"."]}, "2": {}, "3": {}}